[
  {
    "desc_en": "Increases HP by 1.5% of base value (does not include plus/assists)",
    "desc_en_official": "Slightly improves HP",
    "desc_ja": "Untranslated",
    "desc_ja_official": "Unknown",
    "desc_ko": "Untranslated",
    "desc_ko_official": "Unknown",
    "has_120_boost": false,
    "latent_skill_id": 1,
    "name_en": "Improved HP",
    "name_en_official": "Improved HP",
    "name_ja": "Untranslated",
    "name_ja_official": "Unknown",
    "name_ko": "Untranslated",
    "name_ko_official": "Unknown",
    "required_awakening": null,
    "required_level": null,
    "required_types": null,
    "slots": 1
  },
  {
    "desc_en": "Increases ATK by 1% of base value (does not include plus/assists)",
    "desc_en_official": "Slightly improves ATK",
    "desc_ja": "Untranslated",
    "desc_ja_official": "Unknown",
    "desc_ko": "Untranslated",
    "desc_ko_official": "Unknown",
    "has_120_boost": false,
    "latent_skill_id": 2,
    "name_en": "Improved ATK",
    "name_en_official": "Improved ATK",
    "name_ja": "Untranslated",
    "name_ja_official": "Unknown",
    "name_ko": "Untranslated",
    "name_ko_official": "Unknown",
    "required_awakening": null,
    "required_level": null,
    "required_types": null,
    "slots": 1
  },
  {
    "desc_en": "Increases RCV by 5% of base value (does not include plus/assists)",
    "desc_en_official": "Slightly improves RCV",
    "desc_ja": "Untranslated",
    "desc_ja_official": "Unknown",
    "desc_ko": "Untranslated",
    "desc_ko_official": "Unknown",
    "has_120_boost": false,
    "latent_skill_id": 3,
    "name_en": "Improved RCV",
    "name_en_official": "Improved RCV",
    "name_ja": "Untranslated",
    "name_ja_official": "Unknown",
    "name_ko": "Untranslated",
    "name_ko_official": "Unknown",
    "required_awakening": null,
    "required_level": null,
    "required_types": null,
    "slots": 1
  },
  {
    "desc_en": "Extends move time by .05 seconds",
    "desc_en_official": "Extremely slightly extends time to move Orbs",
    "desc_ja": "Untranslated",
    "desc_ja_official": "Unknown",
    "desc_ko": "Untranslated",
    "desc_ko_official": "Unknown",
    "has_120_boost": false,
    "latent_skill_id": 4,
    "name_en": "Extended Move Time",
    "name_en_official": "Extended Move Time",
    "name_ja": "Untranslated",
    "name_ja_official": "Unknown",
    "name_ko": "Untranslated",
    "name_ko_official": "Unknown",
    "required_awakening": null,
    "required_level": null,
    "required_types": null,
    "slots": 1
  },
  {
    "desc_en": "Heals 15% of card's base RCV when matching orbs (does not include plus/assists)",
    "desc_en_official": "Recovers a little HP when matching Orbs (No effect when RCV is 0 or lower)",
    "desc_ja": "Untranslated",
    "desc_ja_official": "Unknown",
    "desc_ko": "Untranslated",
    "desc_ko_official": "Unknown",
    "has_120_boost": false,
    "latent_skill_id": 5,
    "name_en": "Auto Recover",
    "name_en_official": "Auto-RCV",
    "name_ja": "Untranslated",
    "name_ja_official": "Unknown",
    "name_ko": "Untranslated",
    "name_ko_official": "Unknown",
    "required_awakening": null,
    "required_level": null,
    "required_types": null,
    "slots": 1
  },
  {
    "desc_en": "Reduces damage from Fire Att. enemies by 1% (stacks additively with other Fire Resist latents & awakenings)",
    "desc_en_official": "Slightly reduces damage received by Fire Att. enemies",
    "desc_ja": "Untranslated",
    "desc_ja_official": "Unknown",
    "desc_ko": "Untranslated",
    "desc_ko_official": "Unknown",
    "has_120_boost": false,
    "latent_skill_id": 6,
    "name_en": "Fire Damage Reduction",
    "name_en_official": "Fire Damage Reduction",
    "name_ja": "Untranslated",
    "name_ja_official": "Unknown",
    "name_ko": "Untranslated",
    "name_ko_official": "Unknown",
    "required_awakening": null,
    "required_level": null,
    "required_types": null,
    "slots": 1
  },
  {
    "desc_en": "Reduces damage from Water Att. enemies by 1% (stacks additively with other Water Resist latents & awakenings)",
    "desc_en_official": "Slightly reduces damage received by Water Att. enemies",
    "desc_ja": "Untranslated",
    "desc_ja_official": "Unknown",
    "desc_ko": "Untranslated",
    "desc_ko_official": "Unknown",
    "has_120_boost": false,
    "latent_skill_id": 7,
    "name_en": "Water Damage Reduction",
    "name_en_official": "Water Damage Reduction",
    "name_ja": "Untranslated",
    "name_ja_official": "Unknown",
    "name_ko": "Untranslated",
    "name_ko_official": "Unknown",
    "required_awakening": null,
    "required_level": null,
    "required_types": null,
    "slots": 1
  },
  {
    "desc_en": "Reduces damage from Wood Att. enemies by 1% (stacks additively with other Wood Resist latents & awakenings)",
    "desc_en_official": "Slightly reduces damage received by Wood Att. enemies",
    "desc_ja": "Untranslated",
    "desc_ja_official": "Unknown",
    "desc_ko": "Untranslated",
    "desc_ko_official": "Unknown",
    "has_120_boost": false,
    "latent_skill_id": 8,
    "name_en": "Wood Damage Reduction",
    "name_en_official": "Wood Damage Reduction",
    "name_ja": "Untranslated",
    "name_ja_official": "Unknown",
    "name_ko": "Untranslated",
    "name_ko_official": "Unknown",
    "required_awakening": null,
    "required_level": null,
    "required_types": null,
    "slots": 1
  },
  {
    "desc_en": "Reduces damage from Light Att. enemies by 1% (stacks additively with other Light Resist latents & awakenings)",
    "desc_en_official": "Slightly reduces damage received by Light Att. enemies",
    "desc_ja": "Untranslated",
    "desc_ja_official": "Unknown",
    "desc_ko": "Untranslated",
    "desc_ko_official": "Unknown",
    "has_120_boost": false,
    "latent_skill_id": 9,
    "name_en": "Light Damage Reduction",
    "name_en_official": "Light Damage Reduction",
    "name_ja": "Untranslated",
    "name_ja_official": "Unknown",
    "name_ko": "Untranslated",
    "name_ko_official": "Unknown",
    "required_awakening": null,
    "required_level": null,
    "required_types": null,
    "slots": 1
  },
  {
    "desc_en": "Reduces damage from Dark Att. enemies by 1% (stacks additively with other Dark Resist latents & awakenings)",
    "desc_en_official": "Slightly reduces damage received by Dark Att. enemies",
    "desc_ja": "Untranslated",
    "desc_ja_official": "Unknown",
    "desc_ko": "Untranslated",
    "desc_ko_official": "Unknown",
    "has_120_boost": false,
    "latent_skill_id": 10,
    "name_en": "Dark Damage Reduction",
    "name_en_official": "Dark Damage Reduction",
    "name_ja": "Untranslated",
    "name_ja_official": "Unknown",
    "name_ko": "Untranslated",
    "name_ko_official": "Unknown",
    "required_awakening": null,
    "required_level": null,
    "required_types": null,
    "slots": 1
  },
  {
    "desc_en": "Reduces skill delay by 1 turn",
    "desc_en_official": "Reduces skill delay by 1 turn for each Awoken Latent Skill added",
    "desc_ja": "Untranslated",
    "desc_ja_official": "Unknown",
    "desc_ko": "Untranslated",
    "desc_ko_official": "Unknown",
    "has_120_boost": false,
    "latent_skill_id": 11,
    "name_en": "Skill Delay Resistance",
    "name_en_official": "Skill Delay Resistance",
    "name_ja": "Untranslated",
    "name_ja_official": "Unknown",
    "name_ko": "Untranslated",
    "name_ko_official": "Unknown",
    "required_awakening": null,
    "required_level": null,
    "required_types": null,
    "slots": 1
  },
  {
    "desc_en": "Increases HP/ATK/RCV by 3/2/20% of base value (does not include plus/assists)",
    "desc_en_official": "Increases all stats",
    "desc_ja": "Untranslated",
    "desc_ja_official": "Unknown",
    "desc_ko": "Untranslated",
    "desc_ko_official": "Unknown",
    "has_120_boost": false,
    "latent_skill_id": 12,
    "name_en": "All Stats Improved",
    "name_en_official": "All Stats Improved",
    "name_ja": "Untranslated",
    "name_ja_official": "Unknown",
    "name_ko": "Untranslated",
    "name_ko_official": "Unknown",
    "required_awakening": null,
    "required_level": null,
    "required_types": null,
    "slots": 2
  },
  {
    "desc_en": "Completely resists leader change attacks when directed at this card, whether in the sub or leader position",
    "desc_en_official": "Voids Leader Change attacks",
    "desc_ja": "Untranslated",
    "desc_ja_official": "Unknown",
    "desc_ko": "Untranslated",
    "desc_ko_official": "Unknown",
    "has_120_boost": true,
    "latent_skill_id": 13,
    "name_en": "Leader Change Resistance",
    "name_en_official": "Leader Change Resistance",
    "name_ja": "Untranslated",
    "name_ja_official": "Unknown",
    "name_ko": "Untranslated",
    "name_ko_official": "Unknown",
    "required_awakening": null,
    "required_level": null,
    "required_types": null,
    "slots": 6
  },
  {
    "desc_en": "Completely resists jammer skyfall attacks",
    "desc_en_official": "Voids Jammer Surge attacks",
    "desc_ja": "Untranslated",
    "desc_ja_official": "Unknown",
    "desc_ko": "Untranslated",
    "desc_ko_official": "Unknown",
    "has_120_boost": true,
    "latent_skill_id": 14,
    "name_en": "Jammer Surge Resistance",
    "name_en_official": "Jammer Surge Resistance",
    "name_ja": "Untranslated",
    "name_ja_official": "Unknown",
    "name_ko": "Untranslated",
    "name_ko_official": "Unknown",
    "required_awakening": null,
    "required_level": null,
    "required_types": null,
    "slots": 6
  },
  {
    "desc_en": "Completely resists poison skyfall attacks",
    "desc_en_official": "Voids Poison Surge attacks",
    "desc_ja": "Untranslated",
    "desc_ja_official": "Unknown",
    "desc_ko": "Untranslated",
    "desc_ko_official": "Unknown",
    "has_120_boost": true,
    "latent_skill_id": 15,
    "name_en": "Poison Surge Resistance",
    "name_en_official": "Poison Surge Resistance",
    "name_ja": "Untranslated",
    "name_ja_official": "Unknown",
    "name_ko": "Untranslated",
    "name_ko_official": "Unknown",
    "required_awakening": null,
    "required_level": null,
    "required_types": null,
    "slots": 6
  },
  {
    "desc_en": "Increases this card's damage by 3x against Evo Material enemies",
    "desc_en_official": "Increases ATK against Evo Material Types",
    "desc_ja": "Untranslated",
    "desc_ja_official": "Unknown",
    "desc_ko": "Untranslated",
    "desc_ko_official": "Unknown",
    "has_120_boost": false,
    "latent_skill_id": 16,
    "name_en": "Evo Material Killer",
    "name_en_official": "Evo Material Killer",
    "name_ja": "Untranslated",
    "name_ja_official": "Unknown",
    "name_ko": "Untranslated",
    "name_ko_official": "Unknown",
    "required_awakening": null,
    "required_level": null,
    "required_types": null,
    "slots": 2
  },
  {
    "desc_en": "Increases this card's damage by 3x against Awoken Material enemies",
    "desc_en_official": "Increases ATK against Awoken Material Types",
    "desc_ja": "Untranslated",
    "desc_ja_official": "Unknown",
    "desc_ko": "Untranslated",
    "desc_ko_official": "Unknown",
    "has_120_boost": false,
    "latent_skill_id": 17,
    "name_en": "Awoken Material Killer",
    "name_en_official": "Awoken Material Killer",
    "name_ja": "Untranslated",
    "name_ja_official": "Unknown",
    "name_ko": "Untranslated",
    "name_ko_official": "Unknown",
    "required_awakening": null,
    "required_level": null,
    "required_types": null,
    "slots": 2
  },
  {
    "desc_en": "Increases this card's damage by 3x against Enhanced Material enemies",
    "desc_en_official": "Increases ATK against Enhanced Material Types",
    "desc_ja": "Untranslated",
    "desc_ja_official": "Unknown",
    "desc_ko": "Untranslated",
    "desc_ko_official": "Unknown",
    "has_120_boost": false,
    "latent_skill_id": 18,
    "name_en": "Enhanced Material Killer",
    "name_en_official": "Enhanced Material Killer",
    "name_ja": "Untranslated",
    "name_ja_official": "Unknown",
    "name_ko": "Untranslated",
    "name_ko_official": "Unknown",
    "required_awakening": null,
    "required_level": null,
    "required_types": null,
    "slots": 2
  },
  {
    "desc_en": "Increases this card's damage by 3x against Redeemable Material enemies",
    "desc_en_official": "Increases ATK against Redeemable Material Types",
    "desc_ja": "Untranslated",
    "desc_ja_official": "Unknown",
    "desc_ko": "Untranslated",
    "desc_ko_official": "Unknown",
    "has_120_boost": false,
    "latent_skill_id": 19,
    "name_en": "Redeemable Material Killer",
    "name_en_official": "Redeemable Material Killer",
    "name_ja": "Untranslated",
    "name_ja_official": "Unknown",
    "name_ko": "Untranslated",
    "name_ko_official": "Unknown",
    "required_awakening": null,
    "required_level": null,
    "required_types": null,
    "slots": 2
  },
  {
    "desc_en": "Increases this card's damage by 3x against God Type enemies",
    "desc_en_official": "Increases ATK against God Types",
    "desc_ja": "Untranslated",
    "desc_ja_official": "Unknown",
    "desc_ko": "Untranslated",
    "desc_ko_official": "Unknown",
    "has_120_boost": false,
    "latent_skill_id": 20,
    "name_en": "God Killer",
    "name_en_official": "God Killer",
    "name_ja": "Untranslated",
    "name_ja_official": "Unknown",
    "name_ko": "Untranslated",
    "name_ko_official": "Unknown",
    "required_awakening": null,
    "required_level": null,
    "required_types": [7],
    "slots": 2
  },
  {
    "desc_en": "Increases this card's damage by 3x against Dragon Type enemies",
    "desc_en_official": "Increases ATK against Dragon Types",
    "desc_ja": "Untranslated",
    "desc_ja_official": "Unknown",
    "desc_ko": "Untranslated",
    "desc_ko_official": "Unknown",
    "has_120_boost": false,
    "latent_skill_id": 21,
    "name_en": "Dragon Killer",
    "name_en_official": "Dragon Killer",
    "name_ja": "Untranslated",
    "name_ja_official": "Unknown",
    "name_ko": "Untranslated",
    "name_ko_official": "Unknown",
    "required_awakening": null,
    "required_level": null,
    "required_types": [3, 8],
    "slots": 2
  },
  {
    "desc_en": "Increases this card's damage by 3x against Devil Type enemies",
    "desc_en_official": "Increases ATK against Devil Types",
    "desc_ja": "Untranslated",
    "desc_ja_official": "Unknown",
    "desc_ko": "Untranslated",
    "desc_ko_official": "Unknown",
    "has_120_boost": false,
    "latent_skill_id": 22,
    "name_en": "Devil Killer",
    "name_en_official": "Devil Killer",
    "name_ja": "Untranslated",
    "name_ja_official": "Unknown",
    "name_ko": "Untranslated",
    "name_ko_official": "Unknown",
    "required_awakening": null,
    "required_level": null,
    "required_types": [5],
    "slots": 2
  },
  {
    "desc_en": "Increases this card's damage by 3x against Machine Type enemies",
    "desc_en_official": "Increases ATK against Machine Types",
    "desc_ja": "Untranslated",
    "desc_ja_official": "Unknown",
    "desc_ko": "Untranslated",
    "desc_ko_official": "Unknown",
    "has_120_boost": false,
    "latent_skill_id": 23,
    "name_en": "Machine Killer",
    "name_en_official": "Machine Killer",
    "name_ja": "Untranslated",
    "name_ja_official": "Unknown",
    "name_ko": "Untranslated",
    "name_ko_official": "Unknown",
    "required_awakening": null,
    "required_level": null,
    "required_types": [1, 5],
    "slots": 2
  },
  {
    "desc_en": "Increases this card's damage by 3x against Balanced Type enemies",
    "desc_en_official": "Increases ATK against Balanced Types",
    "desc_ja": "Untranslated",
    "desc_ja_official": "Unknown",
    "desc_ko": "Untranslated",
    "desc_ko_official": "Unknown",
    "has_120_boost": false,
    "latent_skill_id": 24,
    "name_en": "Balanced Killer",
    "name_en_official": "Balanced Killer",
    "name_ja": "Untranslated",
    "name_ja_official": "Unknown",
    "name_ko": "Untranslated",
    "name_ko_official": "Unknown",
    "required_awakening": null,
    "required_level": null,
    "required_types": null,
    "slots": 2
  },
  {
    "desc_en": "Increases this card's damage by 3x against Attacker Type enemies",
    "desc_en_official": "Increases ATK against Attacker Types",
    "desc_ja": "Untranslated",
    "desc_ja_official": "Unknown",
    "desc_ko": "Untranslated",
    "desc_ko_official": "Unknown",
    "has_120_boost": false,
    "latent_skill_id": 25,
    "name_en": "Attacker Killer",
    "name_en_official": "Attacker Killer",
    "name_ja": "Untranslated",
    "name_ja_official": "Unknown",
    "name_ko": "Untranslated",
    "name_ko_official": "Unknown",
    "required_awakening": null,
    "required_level": null,
    "required_types": [2, 7],
    "slots": 2
  },
  {
    "desc_en": "Increases this card's damage by 3x against Physical Type enemies",
    "desc_en_official": "Increases ATK against Physical Types",
    "desc_ja": "Untranslated",
    "desc_ja_official": "Unknown",
    "desc_ko": "Untranslated",
    "desc_ko_official": "Unknown",
    "has_120_boost": false,
    "latent_skill_id": 26,
    "name_en": "Physical Killer",
    "name_en_official": "Physical Killer",
    "name_ja": "Untranslated",
    "name_ja_official": "Unknown",
    "name_ko": "Untranslated",
    "name_ko_official": "Unknown",
    "required_awakening": null,
    "required_level": null,
    "required_types": [3, 8],
    "slots": 2
  },
  {
    "desc_en": "Increases this card's damage by 3x against Healer Type enemies",
    "desc_en_official": "Increases ATK against Healer Types",
    "desc_ja": "Untranslated",
    "desc_ja_official": "Unknown",
    "desc_ko": "Untranslated",
    "desc_ko_official": "Unknown",
    "has_120_boost": false,
    "latent_skill_id": 27,
    "name_en": "Healer Killer",
    "name_en_official": "Healer Killer",
    "name_ja": "Untranslated",
    "name_ja_official": "Unknown",
    "name_ko": "Untranslated",
    "name_ko_official": "Unknown",
    "required_awakening": null,
    "required_level": null,
    "required_types": [4, 6],
    "slots": 2
  },
  {
    "desc_en": "Increases HP by 4.5% of base value (does not include plus/assists)",
    "desc_en_official": "Improves HP a little",
    "desc_ja": "Untranslated",
    "desc_ja_official": "Unknown",
    "desc_ko": "Untranslated",
    "desc_ko_official": "Unknown",
    "has_120_boost": false,
    "latent_skill_id": 28,
    "name_en": "Improved HP+",
    "name_en_official": "Improved HP+",
    "name_ja": "Untranslated",
    "name_ja_official": "Unknown",
    "name_ko": "Untranslated",
    "name_ko_official": "Unknown",
    "required_awakening": null,
    "required_level": null,
    "required_types": null,
    "slots": 2
  },
  {
    "desc_en": "Increases ATK by 3% of base value (does not include plus/assists)",
    "desc_en_official": "Improves ATK a little",
    "desc_ja": "Untranslated",
    "desc_ja_official": "Unknown",
    "desc_ko": "Untranslated",
    "desc_ko_official": "Unknown",
    "has_120_boost": false,
    "latent_skill_id": 29,
    "name_en": "Improved ATK+",
    "name_en_official": "Improved ATK+",
    "name_ja": "Untranslated",
    "name_ja_official": "Unknown",
    "name_ko": "Untranslated",
    "name_ko_official": "Unknown",
    "required_awakening": null,
    "required_level": null,
    "required_types": null,
    "slots": 2
  },
  {
    "desc_en": "Increases RCV by 30% of base value (does not include plus/assists)",
    "desc_en_official": "Improves RCV a little",
    "desc_ja": "Untranslated",
    "desc_ja_official": "Unknown",
    "desc_ko": "Untranslated",
    "desc_ko_official": "Unknown",
    "has_120_boost": false,
    "latent_skill_id": 30,
    "name_en": "Improved RCV+",
    "name_en_official": "Improved RCV+",
    "name_ja": "Untranslated",
    "name_ja_official": "Unknown",
    "name_ko": "Untranslated",
    "name_ko_official": "Unknown",
    "required_awakening": null,
    "required_level": null,
    "required_types": null,
    "slots": 2
  }
]
